nebulento/__init__.py
nebulento/bracket_expansion.py
nebulento/container.py
nebulento/domain_engine.py
nebulento/fuzz.py
nebulento/opm.py
nebulento/version.py
nebulento-0.1.0.dist-info/LICENSE.md
nebulento-0.1.0.dist-info/METADATA
nebulento-0.1.0.dist-info/WHEEL
nebulento-0.1.0.dist-info/entry_points.txt
nebulento-0.1.0.dist-info/top_level.txt
nebulento-0.1.0.dist-info/RECORD
