Metadata-Version: 2.1
Name: nebulento
Version: 0.1.0
Summary: dead simple fuzzy matching intent parser
Home-page: https://github.com/OpenJarbas/nebulento
Author: jarbasai
Author-email: jarbasai@mailfence.com
License: apache-2.0
Platform: UNKNOWN
Requires-Dist: rapidfuzz
Requires-Dist: quebra-frases
